[
  {
    "pcgw_name": "Engine:3DMark Vantage",
    "pcgw_url": "//pcgamingwiki.com/wiki/Engine:3DMark_Vantage",
    "wikipedia": "3DMark",
    "wikipedia_url": "https://en.wikipedia.org/wiki/3DMark"
  },
  {
    "pcgw_name": "Engine:3Dream",
    "pcgw_url": "//pcgamingwiki.com/wiki/Engine:3Dream",
    "wikipedia": null,
    "wikipedia_url": null
  },
  {
    "pcgw_name": "Engine:4A Engine",
    "pcgw_url": "//pcgamingwiki.com/wiki/Engine:4A_Engine",
    "wikipedia": "4A Engine",
    "wikipedia_url": "https://en.wikipedia.org/wiki/4A_Engine"
  },
  {
    "pcgw_name": "Engine:A.L.I.V.E.",
    "pcgw_url": "//pcgamingwiki.com/wiki/Engine:A.L.I.V.E.",
    "wikipedia": null,
    "wikipedia_url": null
  },
  {
    "pcgw_name": "Engine:AGI",
    "pcgw_url": "//pcgamingwiki.com/wiki/Engine:AGI",
    "wikipedia": "Adventure_Game_Interpreter",
    "wikipedia_url": "https://en.wikipedia.org/wiki/Adventure_Game_Interpreter"
  },
  {
    "pcgw_name": "Engine:AGen",
    "pcgw_url": "//pcgamingwiki.com/wiki/Engine:AGen",
    "wikipedia": null,
    "wikipedia_url": null
  },
  {
    "pcgw_name": "Engine:AMP",
    "pcgw_url": "//pcgamingwiki.com/wiki/Engine:AMP",
    "wikipedia": null,
    "wikipedia_url": null
  },
  {
    "pcgw_name": "Engine:AVG32",
    "pcgw_url": "//pcgamingwiki.com/wiki/Engine:AVG32",
    "wikipedia": null,
    "wikipedia_url": null
  },
  {
    "pcgw_name": "Engine:Abyss Engine",
    "pcgw_url": "//pcgamingwiki.com/wiki/Engine:Abyss_Engine",
    "wikipedia": null,
    "wikipedia_url": null
  },
  {
    "pcgw_name": "Engine:Adobe AIR",
    "pcgw_url": "//pcgamingwiki.com/wiki/Engine:Adobe_AIR",
    "wikipedia": "Adobe Integrated Runtime",
    "wikipedia_url": "https://en.wikipedia.org/wiki/Adobe_Integrated_Runtime"
  },
  {
    "pcgw_name": "Engine:Adventure Game Studio",
    "pcgw_url": "//pcgamingwiki.com/wiki/Engine:Adventure_Game_Studio",
    "wikipedia": "Adventure Game Studio",
    "wikipedia_url": "https://en.wikipedia.org/wiki/Adventure_Game_Studio"
  },
  {
    "pcgw_name": "Engine:Alamo Game Engine",
    "pcgw_url": "//pcgamingwiki.com/wiki/Engine:Alamo_Game_Engine",
    "wikipedia": "Petroglyph Games#Alamo Game Engine",
    "wikipedia_url": "https://en.wikipedia.org/wiki/Petroglyph_Games#Alamo_Game_Engine"
  },
  {
    "pcgw_name": "Engine:Amazon Lumberyard",
    "pcgw_url": "//pcgamingwiki.com/wiki/Engine:Amazon_Lumberyard",
    "wikipedia": "Amazon Lumberyard",
    "wikipedia_url": "https://en.wikipedia.org/wiki/Amazon_Lumberyard"
  },
  {
    "pcgw_name": "Engine:Angel Game Engine",
    "pcgw_url": "//pcgamingwiki.com/wiki/Engine:Angel_Game_Engine",
    "wikipedia": null,
    "wikipedia_url": null
  },
  {
    "pcgw_name": "Engine:Anvil",
    "pcgw_url": "//pcgamingwiki.com/wiki/Engine:Anvil",
    "wikipedia": "Anvil (game engine)",
    "wikipedia_url": "https://en.wikipedia.org/wiki/Anvil_(game_engine)"
  },
  {
    "pcgw_name": "Engine:AnvilNext",
    "pcgw_url": "//pcgamingwiki.com/wiki/Engine:AnvilNext",
    "wikipedia": "Anvil (game engine)",
    "wikipedia_url": "https://en.wikipedia.org/wiki/Anvil_(game_engine)"
  },
  {
    "pcgw_name": "Engine:Apex Engine",
    "pcgw_url": "//pcgamingwiki.com/wiki/Engine:Apex_Engine",
    "wikipedia": null,
    "wikipedia_url": null
  },
  {
    "pcgw_name": "Engine:Asura",
    "pcgw_url": "//pcgamingwiki.com/wiki/Engine:Asura",
    "wikipedia": null,
    "wikipedia_url": null
  },
  {
    "pcgw_name": "Engine:AtmosFear",
    "pcgw_url": "//pcgamingwiki.com/wiki/Engine:AtmosFear",
    "wikipedia": null,
    "wikipedia_url": null
  },
  {
    "pcgw_name": "Engine:Atrophy",
    "pcgw_url": "//pcgamingwiki.com/wiki/Engine:Atrophy",
    "wikipedia": null,
    "wikipedia_url": null
  },
  {
    "pcgw_name": "Engine:Aurora",
    "pcgw_url": "//pcgamingwiki.com/wiki/Engine:Aurora",
    "wikipedia": "BioWare#Technology",
    "wikipedia_url": "https://en.wikipedia.org/wiki/BioWare#Technology"
  },
  {
    "pcgw_name": "Engine:Autodesk Stingray Engine",
    "pcgw_url": "//pcgamingwiki.com/wiki/Engine:Autodesk_Stingray_Engine",
    "wikipedia": "Bitsquid",
    "wikipedia_url": "https://en.wikipedia.org/wiki/Bitsquid"
  },
  {
    "pcgw_name": "Engine:Avalanche Engine",
    "pcgw_url": "//pcgamingwiki.com/wiki/Engine:Avalanche_Engine",
    "wikipedia": null,
    "wikipedia_url": null
  },
  {
    "pcgw_name": "Engine:Avalanche Engine 2.0",
    "pcgw_url": "//pcgamingwiki.com/wiki/Engine:Avalanche_Engine_2.0",
    "wikipedia": null,
    "wikipedia_url": null
  },
  {
    "pcgw_name": "Engine:Avalanche Engine 3.0",
    "pcgw_url": "//pcgamingwiki.com/wiki/Engine:Avalanche_Engine_3.0",
    "wikipedia": null,
    "wikipedia_url": null
  },
  {
    "pcgw_name": "Engine:BANG!",
    "pcgw_url": "//pcgamingwiki.com/wiki/Engine:BANG!",
    "wikipedia": null,
    "wikipedia_url": null
  },
  {
    "pcgw_name": "Engine:BEARD",
    "pcgw_url": "//pcgamingwiki.com/wiki/Engine:BEARD",
    "wikipedia": "Twisted_Pixel_Games#Technology",
    "wikipedia_url": "https://en.wikipedia.org/wiki/Twisted_Pixel_Games#Technology"
  },
  {
    "pcgw_name": "Engine:Beelzebub",
    "pcgw_url": "//pcgamingwiki.com/wiki/Engine:Beelzebub",
    "wikipedia": null,
    "wikipedia_url": null
  },
  {
    "pcgw_name": "Engine:Blazing Renderer",
    "pcgw_url": "//pcgamingwiki.com/wiki/Engine:Blazing_Renderer",
    "wikipedia": "Argonaut_Games#BRender",
    "wikipedia_url": "https://en.wikipedia.org/wiki/Argonaut_Games#BRender"
  },
  {
    "pcgw_name": "Engine:Blitz3D",
    "pcgw_url": "//pcgamingwiki.com/wiki/Engine:Blitz3D",
    "wikipedia": "Blitz BASIC#Blitz3D_SDK",
    "wikipedia_url": "https://en.wikipedia.org/wiki/Blitz_BASIC#Blitz3D_SDK"
  },
  {
    "pcgw_name": "Engine:Bluepoint Engine",
    "pcgw_url": "//pcgamingwiki.com/wiki/Engine:Bluepoint_Engine",
    "wikipedia": null,
    "wikipedia_url": null
  },
  {
    "pcgw_name": "Engine:Bright Light Halogen",
    "pcgw_url": "//pcgamingwiki.com/wiki/Engine:Bright_Light_Halogen",
    "wikipedia": null,
    "wikipedia_url": null
  },
  {
    "pcgw_name": "Engine:Buddha",
    "pcgw_url": "//pcgamingwiki.com/wiki/Engine:Buddha",
    "wikipedia": null,
    "wikipedia_url": null
  },
  {
    "pcgw_name": "Engine:Build",
    "pcgw_url": "//pcgamingwiki.com/wiki/Engine:Build",
    "wikipedia": "Build (game engine)",
    "wikipedia_url": "https://en.wikipedia.org/wiki/Build_(game_engine)"
  },
  {
    "pcgw_name": "Engine:CANVAS",
    "pcgw_url": "//pcgamingwiki.com/wiki/Engine:CANVAS",
    "wikipedia": null,
    "wikipedia_url": null
  },
  {
    "pcgw_name": "Engine:CATHODE",
    "pcgw_url": "//pcgamingwiki.com/wiki/Engine:CATHODE",
    "wikipedia": null,
    "wikipedia_url": null
  },
  {
    "pcgw_name": "Engine:CPAL3D",
    "pcgw_url": "//pcgamingwiki.com/wiki/Engine:CPAL3D",
    "wikipedia": null,
    "wikipedia_url": null
  },
  {
    "pcgw_name": "Engine:CTG",
    "pcgw_url": "//pcgamingwiki.com/wiki/Engine:CTG",
    "wikipedia": null,
    "wikipedia_url": null
  },
  {
    "pcgw_name": "Engine:CatSystem2",
    "pcgw_url": "//pcgamingwiki.com/wiki/Engine:CatSystem2",
    "wikipedia": null,
    "wikipedia_url": null
  },
  {
    "pcgw_name": "Engine:Chameleon",
    "pcgw_url": "//pcgamingwiki.com/wiki/Engine:Chameleon",
    "wikipedia": null,
    "wikipedia_url": null
  },
  {
    "pcgw_name": "Engine:Chrome Engine",
    "pcgw_url": "//pcgamingwiki.com/wiki/Engine:Chrome_Engine",
    "wikipedia": "Chrome Engine",
    "wikipedia_url": "https://en.wikipedia.org/wiki/Chrome_Engine"
  },
  {
    "pcgw_name": "Engine:Clausewitz",
    "pcgw_url": "//pcgamingwiki.com/wiki/Engine:Clausewitz",
    "wikipedia": "Paradox Development Studio#Clausewitz Engine",
    "wikipedia_url": "https://en.wikipedia.org/wiki/Paradox_Development_Studio#Clausewitz_Engine"
  },
  {
    "pcgw_name": "Engine:Clickteam Fusion",
    "pcgw_url": "//pcgamingwiki.com/wiki/Engine:Clickteam_Fusion",
    "wikipedia": "Clickteam",
    "wikipedia_url": "https://en.wikipedia.org/wiki/Clickteam"
  },
  {
    "pcgw_name": "Engine:CloakNT",
    "pcgw_url": "//pcgamingwiki.com/wiki/Engine:CloakNT",
    "wikipedia": null,
    "wikipedia_url": null
  },
  {
    "pcgw_name": "Engine:Cobra",
    "pcgw_url": "//pcgamingwiki.com/wiki/Engine:Cobra",
    "wikipedia": null,
    "wikipedia_url": null
  },
  {
    "pcgw_name": "Engine:Cocos2d",
    "pcgw_url": "//pcgamingwiki.com/wiki/Engine:Cocos2d",
    "wikipedia": "Cocos2d",
    "wikipedia_url": "https://en.wikipedia.org/wiki/Cocos2d"
  },
  {
    "pcgw_name": "Engine:Construct 2",
    "pcgw_url": "//pcgamingwiki.com/wiki/Engine:Construct_2",
    "wikipedia": "Construct (game engine)#Construct 2",
    "wikipedia_url": "https://en.wikipedia.org/wiki/Construct_(game_engine)#Construct_2"
  },
  {
    "pcgw_name": "Engine:Construct 3",
    "pcgw_url": "//pcgamingwiki.com/wiki/Engine:Construct_3",
    "wikipedia": "Construct (game engine)#Construct 3",
    "wikipedia_url": "https://en.wikipedia.org/wiki/Construct_(game_engine)#Construct_3"
  },
  {
    "pcgw_name": "Engine:Construct Classic",
    "pcgw_url": "//pcgamingwiki.com/wiki/Engine:Construct_Classic",
    "wikipedia": "Construct (game engine)#Construct Classic",
    "wikipedia_url": "https://en.wikipedia.org/wiki/Construct_(game_engine)#Construct_Classic"
  },
  {
    "pcgw_name": "Engine:Creation Engine",
    "pcgw_url": "//pcgamingwiki.com/wiki/Engine:Creation_Engine",
    "wikipedia": "Creation Engine",
    "wikipedia_url": "https://en.wikipedia.org/wiki/Creation_Engine"
  },
  {
    "pcgw_name": "Engine:CryEngine",
    "pcgw_url": "//pcgamingwiki.com/wiki/Engine:CryEngine",
    "wikipedia": "CryEngine#CryEngine 1",
    "wikipedia_url": "https://en.wikipedia.org/wiki/CryEngine#CryEngine_1"
  },
  {
    "pcgw_name": "Engine:CryEngine (4th generation)",
    "pcgw_url": "//pcgamingwiki.com/wiki/Engine:CryEngine_(4th_generation)",
    "wikipedia": "Cryengine#CryEngine_.283.6.E2.80.934.29",
    "wikipedia_url": "https://en.wikipedia.org/wiki/Cryengine#CryEngine_.283.6.E2.80.934.29"
  },
  {
    "pcgw_name": "Engine:CryEngine 2",
    "pcgw_url": "//pcgamingwiki.com/wiki/Engine:CryEngine_2",
    "wikipedia": "CryEngine#CryEngine 2",
    "wikipedia_url": "https://en.wikipedia.org/wiki/CryEngine#CryEngine_2"
  },
  {
    "pcgw_name": "Engine:CryEngine 3",
    "pcgw_url": "//pcgamingwiki.com/wiki/Engine:CryEngine_3",
    "wikipedia": "CryEngine#CryEngine 3",
    "wikipedia_url": "https://en.wikipedia.org/wiki/CryEngine#CryEngine_3"
  },
  {
    "pcgw_name": "Engine:CryEngine V",
    "pcgw_url": "//pcgamingwiki.com/wiki/Engine:CryEngine_V",
    "wikipedia": "CryEngine#CryEngine V",
    "wikipedia_url": "https://en.wikipedia.org/wiki/CryEngine#CryEngine_V"
  },
  {
    "pcgw_name": "Engine:Crystal Engine",
    "pcgw_url": "//pcgamingwiki.com/wiki/Engine:Crystal_Engine",
    "wikipedia": null,
    "wikipedia_url": null
  },
  {
    "pcgw_name": "Engine:Crystal Tools",
    "pcgw_url": "//pcgamingwiki.com/wiki/Engine:Crystal_Tools",
    "wikipedia": "Crystal Tools",
    "wikipedia_url": "https://en.wikipedia.org/wiki/Crystal_Tools"
  },
  {
    "pcgw_name": "Engine:Cube",
    "pcgw_url": "//pcgamingwiki.com/wiki/Engine:Cube",
    "wikipedia": "Cube (video game)#Game engine",
    "wikipedia_url": "https://en.wikipedia.org/wiki/Cube_(video_game)#Game_engine"
  },
  {
    "pcgw_name": "Engine:D.U.N.E.",
    "pcgw_url": "//pcgamingwiki.com/wiki/Engine:D.U.N.E.",
    "wikipedia": null,
    "wikipedia_url": null
  },
  {
    "pcgw_name": "Engine:DS2 Engine",
    "pcgw_url": "//pcgamingwiki.com/wiki/Engine:DS2_Engine",
    "wikipedia": null,
    "wikipedia_url": null
  },
  {
    "pcgw_name": "Engine:Dark Engine",
    "pcgw_url": "//pcgamingwiki.com/wiki/Engine:Dark_Engine",
    "wikipedia": "Dark Engine",
    "wikipedia_url": "https://en.wikipedia.org/wiki/Dark_Engine"
  },
  {
    "pcgw_name": "Engine:DarkPlaces",
    "pcgw_url": "//pcgamingwiki.com/wiki/Engine:DarkPlaces",
    "wikipedia": "DarkPlaces_engine",
    "wikipedia_url": "https://en.wikipedia.org/wiki/DarkPlaces_engine"
  },
  {
    "pcgw_name": "Engine:Dawn Engine",
    "pcgw_url": "//pcgamingwiki.com/wiki/Engine:Dawn_Engine",
    "wikipedia": null,
    "wikipedia_url": null
  },
  {
    "pcgw_name": "Engine:Diesel",
    "pcgw_url": "//pcgamingwiki.com/wiki/Engine:Diesel",
    "wikipedia": "Diesel (game engine)",
    "wikipedia_url": "https://en.wikipedia.org/wiki/Diesel_(game_engine)"
  },
  {
    "pcgw_name": "Engine:Disrupt",
    "pcgw_url": "//pcgamingwiki.com/wiki/Engine:Disrupt",
    "wikipedia": null,
    "wikipedia_url": null
  },
  {
    "pcgw_name": "Engine:Dunia",
    "pcgw_url": "//pcgamingwiki.com/wiki/Engine:Dunia",
    "wikipedia": "Dunia Engine",
    "wikipedia_url": "https://en.wikipedia.org/wiki/Dunia_Engine"
  },
  {
    "pcgw_name": "Engine:Dunia 2",
    "pcgw_url": "//pcgamingwiki.com/wiki/Engine:Dunia_2",
    "wikipedia": "Dunia Engine",
    "wikipedia_url": "https://en.wikipedia.org/wiki/Dunia_Engine"
  },
  {
    "pcgw_name": "Engine:EAGL",
    "pcgw_url": "//pcgamingwiki.com/wiki/Engine:EAGL",
    "wikipedia": "EA Canada#EA Graphics Library",
    "wikipedia_url": "https://en.wikipedia.org/wiki/EA_Canada#EA_Graphics_Library"
  },
  {
    "pcgw_name": "Engine:EAGL 2",
    "pcgw_url": "//pcgamingwiki.com/wiki/Engine:EAGL_2",
    "wikipedia": "EA Canada#EA Graphics Library",
    "wikipedia_url": "https://en.wikipedia.org/wiki/EA_Canada#EA_Graphics_Library"
  },
  {
    "pcgw_name": "Engine:EAGL 3",
    "pcgw_url": "//pcgamingwiki.com/wiki/Engine:EAGL_3",
    "wikipedia": "EA Canada#EA Graphics Library",
    "wikipedia_url": "https://en.wikipedia.org/wiki/EA_Canada#EA_Graphics_Library"
  },
  {
    "pcgw_name": "Engine:EAGL 4",
    "pcgw_url": "//pcgamingwiki.com/wiki/Engine:EAGL_4",
    "wikipedia": "EA Canada#EA Graphics Library",
    "wikipedia_url": "https://en.wikipedia.org/wiki/EA_Canada#EA_Graphics_Library"
  },
  {
    "pcgw_name": "Engine:EGO",
    "pcgw_url": "//pcgamingwiki.com/wiki/Engine:EGO",
    "wikipedia": "EGO (game engine)",
    "wikipedia_url": "https://en.wikipedia.org/wiki/EGO_(game_engine)"
  },
  {
    "pcgw_name": "Engine:Eclipse",
    "pcgw_url": "//pcgamingwiki.com/wiki/Engine:Eclipse",
    "wikipedia": "BioWare#Technology",
    "wikipedia_url": "https://en.wikipedia.org/wiki/BioWare#Technology"
  },
  {
    "pcgw_name": "Engine:Eclipse Engine",
    "pcgw_url": "//pcgamingwiki.com/wiki/Engine:Eclipse_Engine",
    "wikipedia": "Digital Eclipse Software",
    "wikipedia_url": "https://en.wikipedia.org/wiki/Digital_Eclipse_Software"
  },
  {
    "pcgw_name": "Engine:Emmersion",
    "pcgw_url": "//pcgamingwiki.com/wiki/Engine:Emmersion",
    "wikipedia": null,
    "wikipedia_url": null
  },
  {
    "pcgw_name": "Engine:Enforce",
    "pcgw_url": "//pcgamingwiki.com/wiki/Engine:Enforce",
    "wikipedia": null,
    "wikipedia_url": null
  },
  {
    "pcgw_name": "Engine:EngineBlack",
    "pcgw_url": "//pcgamingwiki.com/wiki/Engine:EngineBlack",
    "wikipedia": null,
    "wikipedia_url": null
  },
  {
    "pcgw_name": "Engine:Enigma Engine",
    "pcgw_url": "//pcgamingwiki.com/wiki/Engine:Enigma_Engine",
    "wikipedia": "Enigma Engine",
    "wikipedia_url": "https://en.wikipedia.org/wiki/Enigma_Engine"
  },
  {
    "pcgw_name": "Engine:Esenthel",
    "pcgw_url": "//pcgamingwiki.com/wiki/Engine:Esenthel",
    "wikipedia": null,
    "wikipedia_url": null
  },
  {
    "pcgw_name": "Engine:Essence Engine",
    "pcgw_url": "//pcgamingwiki.com/wiki/Engine:Essence_Engine",
    "wikipedia": "Essence Engine",
    "wikipedia_url": "https://en.wikipedia.org/wiki/Essence_Engine"
  },
  {
    "pcgw_name": "Engine:Europa",
    "pcgw_url": "//pcgamingwiki.com/wiki/Engine:Europa",
    "wikipedia": null,
    "wikipedia_url": null
  },
  {
    "pcgw_name": "Engine:Evolution",
    "pcgw_url": "//pcgamingwiki.com/wiki/Engine:Evolution",
    "wikipedia": null,
    "wikipedia_url": null
  },
  {
    "pcgw_name": "Engine:Evolution (Extreme FX)",
    "pcgw_url": "//pcgamingwiki.com/wiki/Engine:Evolution_(Extreme_FX)",
    "wikipedia": null,
    "wikipedia_url": null
  },
  {
    "pcgw_name": "Engine:FNA",
    "pcgw_url": "//pcgamingwiki.com/wiki/Engine:FNA",
    "wikipedia": null,
    "wikipedia_url": null
  },
  {
    "pcgw_name": "Engine:FPS Creator",
    "pcgw_url": "//pcgamingwiki.com/wiki/Engine:FPS_Creator",
    "wikipedia": "The Game Creators",
    "wikipedia_url": "https://en.wikipedia.org/wiki/The_Game_Creators"
  },
  {
    "pcgw_name": "Engine:Fallout Engine",
    "pcgw_url": "//pcgamingwiki.com/wiki/Engine:Fallout_Engine",
    "wikipedia": null,
    "wikipedia_url": null
  },
  {
    "pcgw_name": "Engine:Firebird Engine",
    "pcgw_url": "//pcgamingwiki.com/wiki/Engine:Firebird_Engine",
    "wikipedia": null,
    "wikipedia_url": null
  },
  {
    "pcgw_name": "Engine:Flash",
    "pcgw_url": "//pcgamingwiki.com/wiki/Engine:Flash",
    "wikipedia": "Adobe Flash",
    "wikipedia_url": "https://en.wikipedia.org/wiki/Adobe_Flash"
  },
  {
    "pcgw_name": "Engine:Fledge",
    "pcgw_url": "//pcgamingwiki.com/wiki/Engine:Fledge",
    "wikipedia": null,
    "wikipedia_url": null
  },
  {
    "pcgw_name": "Engine:Forge",
    "pcgw_url": "//pcgamingwiki.com/wiki/Engine:Forge",
    "wikipedia": null,
    "wikipedia_url": null
  },
  {
    "pcgw_name": "Engine:Forgelight Engine",
    "pcgw_url": "//pcgamingwiki.com/wiki/Engine:Forgelight_Engine",
    "wikipedia": "Forgelight Engine",
    "wikipedia_url": "https://en.wikipedia.org/wiki/Forgelight_Engine"
  },
  {
    "pcgw_name": "Engine:ForzaTech",
    "pcgw_url": "//pcgamingwiki.com/wiki/Engine:ForzaTech",
    "wikipedia": null,
    "wikipedia_url": null
  },
  {
    "pcgw_name": "Engine:Fox Engine",
    "pcgw_url": "//pcgamingwiki.com/wiki/Engine:Fox_Engine",
    "wikipedia": "Fox Engine",
    "wikipedia_url": "https://en.wikipedia.org/wiki/Fox_Engine"
  },
  {
    "pcgw_name": "Engine:Freescape",
    "pcgw_url": "//pcgamingwiki.com/wiki/Engine:Freescape",
    "wikipedia": "Freescape",
    "wikipedia_url": "https://en.wikipedia.org/wiki/Freescape"
  },
  {
    "pcgw_name": "Engine:Frostbite 1.5",
    "pcgw_url": "//pcgamingwiki.com/wiki/Engine:Frostbite_1.5",
    "wikipedia": "Frostbite (game engine)",
    "wikipedia_url": "https://en.wikipedia.org/wiki/Frostbite_(game_engine)"
  },
  {
    "pcgw_name": "Engine:Frostbite 2",
    "pcgw_url": "//pcgamingwiki.com/wiki/Engine:Frostbite_2",
    "wikipedia": "Frostbite (game engine)",
    "wikipedia_url": "https://en.wikipedia.org/wiki/Frostbite_(game_engine)"
  },
  {
    "pcgw_name": "Engine:Frostbite 3",
    "pcgw_url": "//pcgamingwiki.com/wiki/Engine:Frostbite_3",
    "wikipedia": "Frostbite (game engine)",
    "wikipedia_url": "https://en.wikipedia.org/wiki/Frostbite_(game_engine)"
  },
  {
    "pcgw_name": "Engine:GODS",
    "pcgw_url": "//pcgamingwiki.com/wiki/Engine:GODS",
    "wikipedia": null,
    "wikipedia_url": null
  },
  {
    "pcgw_name": "Engine:GameBaker",
    "pcgw_url": "//pcgamingwiki.com/wiki/Engine:GameBaker",
    "wikipedia": null,
    "wikipedia_url": null
  },
  {
    "pcgw_name": "Engine:GameMaker",
    "pcgw_url": "//pcgamingwiki.com/wiki/Engine:GameMaker",
    "wikipedia": "GameMaker: Studio",
    "wikipedia_url": "https://en.wikipedia.org/wiki/GameMaker:_Studio"
  },
  {
    "pcgw_name": "Engine:Gamebryo",
    "pcgw_url": "//pcgamingwiki.com/wiki/Engine:Gamebryo",
    "wikipedia": "Gamebryo",
    "wikipedia_url": "https://en.wikipedia.org/wiki/Gamebryo"
  },
  {
    "pcgw_name": "Engine:Genesis3D",
    "pcgw_url": "//pcgamingwiki.com/wiki/Engine:Genesis3D",
    "wikipedia": "Genesis3D",
    "wikipedia_url": "https://en.wikipedia.org/wiki/Genesis3D"
  },
  {
    "pcgw_name": "Engine:Genie",
    "pcgw_url": "//pcgamingwiki.com/wiki/Engine:Genie",
    "wikipedia": "Genie Engine",
    "wikipedia_url": "https://en.wikipedia.org/wiki/Genie_Engine"
  },
  {
    "pcgw_name": "Engine:Geo-Mod",
    "pcgw_url": "//pcgamingwiki.com/wiki/Engine:Geo-Mod",
    "wikipedia": "Geo-Mod",
    "wikipedia_url": "https://en.wikipedia.org/wiki/Geo-Mod"
  },
  {
    "pcgw_name": "Engine:Glacier",
    "pcgw_url": "//pcgamingwiki.com/wiki/Engine:Glacier",
    "wikipedia": null,
    "wikipedia_url": null
  },
  {
    "pcgw_name": "Engine:Glacier 2",
    "pcgw_url": "//pcgamingwiki.com/wiki/Engine:Glacier_2",
    "wikipedia": null,
    "wikipedia_url": null
  },
  {
    "pcgw_name": "Engine:GlassBox",
    "pcgw_url": "//pcgamingwiki.com/wiki/Engine:GlassBox",
    "wikipedia": null,
    "wikipedia_url": null
  },
  {
    "pcgw_name": "Engine:GlyphX",
    "pcgw_url": "//pcgamingwiki.com/wiki/Engine:GlyphX",
    "wikipedia": null,
    "wikipedia_url": null
  },
  {
    "pcgw_name": "Engine:Gob",
    "pcgw_url": "//pcgamingwiki.com/wiki/Engine:Gob",
    "wikipedia": null,
    "wikipedia_url": null
  },
  {
    "pcgw_name": "Engine:Godot",
    "pcgw_url": "//pcgamingwiki.com/wiki/Engine:Godot",
    "wikipedia": "Godot (game engine)",
    "wikipedia_url": "https://en.wikipedia.org/wiki/Godot_(game_engine)"
  },
  {
    "pcgw_name": "Engine:Gold Box",
    "pcgw_url": "//pcgamingwiki.com/wiki/Engine:Gold_Box",
    "wikipedia": "Gold Box",
    "wikipedia_url": "https://en.wikipedia.org/wiki/Gold_Box"
  },
  {
    "pcgw_name": "Engine:GoldSrc",
    "pcgw_url": "//pcgamingwiki.com/wiki/Engine:GoldSrc",
    "wikipedia": "GoldSrc",
    "wikipedia_url": "https://en.wikipedia.org/wiki/GoldSrc"
  },
  {
    "pcgw_name": "Engine:Goliath Engine",
    "pcgw_url": "//pcgamingwiki.com/wiki/Engine:Goliath_Engine",
    "wikipedia": null,
    "wikipedia_url": null
  },
  {
    "pcgw_name": "Engine:GrimE",
    "pcgw_url": "//pcgamingwiki.com/wiki/Engine:GrimE",
    "wikipedia": null,
    "wikipedia_url": null
  },
  {
    "pcgw_name": "Engine:HPL Engine",
    "pcgw_url": "//pcgamingwiki.com/wiki/Engine:HPL_Engine",
    "wikipedia": "HPL Engine",
    "wikipedia_url": "https://en.wikipedia.org/wiki/HPL_Engine"
  },
  {
    "pcgw_name": "Engine:Halo Engine",
    "pcgw_url": "//pcgamingwiki.com/wiki/Engine:Halo_Engine",
    "wikipedia": null,
    "wikipedia_url": null
  },
  {
    "pcgw_name": "Engine:Hedgehog Engine",
    "pcgw_url": "//pcgamingwiki.com/wiki/Engine:Hedgehog_Engine",
    "wikipedia": "Hedgehog Engine",
    "wikipedia_url": "https://en.wikipedia.org/wiki/Hedgehog_Engine"
  },
  {
    "pcgw_name": "Engine:HeroEngine",
    "pcgw_url": "//pcgamingwiki.com/wiki/Engine:HeroEngine",
    "wikipedia": "HeroEngine",
    "wikipedia_url": "https://en.wikipedia.org/wiki/HeroEngine"
  },
  {
    "pcgw_name": "Engine:Hugo",
    "pcgw_url": "//pcgamingwiki.com/wiki/Engine:Hugo",
    "wikipedia": null,
    "wikipedia_url": null
  },
  {
    "pcgw_name": "Engine:INSANE",
    "pcgw_url": "//pcgamingwiki.com/wiki/Engine:INSANE",
    "wikipedia": "INSANE (software)",
    "wikipedia_url": "https://en.wikipedia.org/wiki/INSANE_(software)"
  },
  {
    "pcgw_name": "Engine:IRISZOOM",
    "pcgw_url": "//pcgamingwiki.com/wiki/Engine:IRISZOOM",
    "wikipedia": null,
    "wikipedia_url": null
  },
  {
    "pcgw_name": "Engine:IW engine",
    "pcgw_url": "//pcgamingwiki.com/wiki/Engine:IW_engine",
    "wikipedia": "IW engine",
    "wikipedia_url": "https://en.wikipedia.org/wiki/IW_engine"
  },
  {
    "pcgw_name": "Engine:Ice-Peak Engine",
    "pcgw_url": "//pcgamingwiki.com/wiki/Engine:Ice-Peak_Engine",
    "wikipedia": null,
    "wikipedia_url": null
  },
  {
    "pcgw_name": "Engine:Id Tech 1",
    "pcgw_url": "//pcgamingwiki.com/wiki/Engine:Id_Tech_1",
    "wikipedia": "Id Tech 1",
    "wikipedia_url": "https://en.wikipedia.org/wiki/Id_Tech_1"
  },
  {
    "pcgw_name": "Engine:Id Tech 2",
    "pcgw_url": "//pcgamingwiki.com/wiki/Engine:Id_Tech_2",
    "wikipedia": "Quake II engine",
    "wikipedia_url": "https://en.wikipedia.org/wiki/Quake_II_engine"
  },
  {
    "pcgw_name": "Engine:Id Tech 3",
    "pcgw_url": "//pcgamingwiki.com/wiki/Engine:Id_Tech_3",
    "wikipedia": "Id Tech 3",
    "wikipedia_url": "https://en.wikipedia.org/wiki/Id_Tech_3"
  },
  {
    "pcgw_name": "Engine:Id Tech 4",
    "pcgw_url": "//pcgamingwiki.com/wiki/Engine:Id_Tech_4",
    "wikipedia": "Id tech 4",
    "wikipedia_url": "https://en.wikipedia.org/wiki/Id_tech_4"
  },
  {
    "pcgw_name": "Engine:Id Tech 5",
    "pcgw_url": "//pcgamingwiki.com/wiki/Engine:Id_Tech_5",
    "wikipedia": "Id Tech 5",
    "wikipedia_url": "https://en.wikipedia.org/wiki/Id_Tech_5"
  },
  {
    "pcgw_name": "Engine:Id Tech 6",
    "pcgw_url": "//pcgamingwiki.com/wiki/Engine:Id_Tech_6",
    "wikipedia": "Id Tech 6",
    "wikipedia_url": "https://en.wikipedia.org/wiki/Id_Tech_6"
  },
  {
    "pcgw_name": "Engine:Id Tech 7",
    "pcgw_url": "//pcgamingwiki.com/wiki/Engine:Id_Tech_7",
    "wikipedia": null,
    "wikipedia_url": null
  },
  {
    "pcgw_name": "Engine:Ignite",
    "pcgw_url": "//pcgamingwiki.com/wiki/Engine:Ignite",
    "wikipedia": "Ignite (game engine)",
    "wikipedia_url": "https://en.wikipedia.org/wiki/Ignite_(game_engine)"
  },
  {
    "pcgw_name": "Engine:Illusion Engine",
    "pcgw_url": "//pcgamingwiki.com/wiki/Engine:Illusion_Engine",
    "wikipedia": null,
    "wikipedia_url": null
  },
  {
    "pcgw_name": "Engine:Impact",
    "pcgw_url": "//pcgamingwiki.com/wiki/Engine:Impact",
    "wikipedia": null,
    "wikipedia_url": null
  },
  {
    "pcgw_name": "Engine:Infernal Engine",
    "pcgw_url": "//pcgamingwiki.com/wiki/Engine:Infernal_Engine",
    "wikipedia": null,
    "wikipedia_url": null
  },
  {
    "pcgw_name": "Engine:Infinity",
    "pcgw_url": "//pcgamingwiki.com/wiki/Engine:Infinity",
    "wikipedia": "BioWare#Technology",
    "wikipedia_url": "https://en.wikipedia.org/wiki/BioWare#Technology"
  },
  {
    "pcgw_name": "Engine:Insanity 3D",
    "pcgw_url": "//pcgamingwiki.com/wiki/Engine:Insanity_3D",
    "wikipedia": null,
    "wikipedia_url": null
  },
  {
    "pcgw_name": "Engine:Invictus Engine",
    "pcgw_url": "//pcgamingwiki.com/wiki/Engine:Invictus_Engine",
    "wikipedia": null,
    "wikipedia_url": null
  },
  {
    "pcgw_name": "Engine:Iron Engine",
    "pcgw_url": "//pcgamingwiki.com/wiki/Engine:Iron_Engine",
    "wikipedia": "Iron Engine",
    "wikipedia_url": "https://en.wikipedia.org/wiki/Iron_Engine"
  },
  {
    "pcgw_name": "Engine:JMonkeyEngine",
    "pcgw_url": "//pcgamingwiki.com/wiki/Engine:JMonkeyEngine",
    "wikipedia": "JMonkeyEngine",
    "wikipedia_url": "https://en.wikipedia.org/wiki/JMonkeyEngine"
  },
  {
    "pcgw_name": "Engine:Jade",
    "pcgw_url": "//pcgamingwiki.com/wiki/Engine:Jade",
    "wikipedia": "Jade_engine",
    "wikipedia_url": "https://en.wikipedia.org/wiki/Jade_engine"
  },
  {
    "pcgw_name": "Engine:Jedi",
    "pcgw_url": "//pcgamingwiki.com/wiki/Engine:Jedi",
    "wikipedia": "Jedi (game engine)",
    "wikipedia_url": "https://en.wikipedia.org/wiki/Jedi_(game_engine)"
  },
  {
    "pcgw_name": "Engine:Kex Engine",
    "pcgw_url": "//pcgamingwiki.com/wiki/Engine:Kex_Engine",
    "wikipedia": null,
    "wikipedia_url": null
  },
  {
    "pcgw_name": "Engine:KiriKiri",
    "pcgw_url": "//pcgamingwiki.com/wiki/Engine:KiriKiri",
    "wikipedia": "KiriKiri",
    "wikipedia_url": "https://en.wikipedia.org/wiki/KiriKiri"
  },
  {
    "pcgw_name": "Engine:KiriKiri Z",
    "pcgw_url": "//pcgamingwiki.com/wiki/Engine:KiriKiri_Z",
    "wikipedia": null,
    "wikipedia_url": null
  },
  {
    "pcgw_name": "Engine:Kyra",
    "pcgw_url": "//pcgamingwiki.com/wiki/Engine:Kyra",
    "wikipedia": null,
    "wikipedia_url": null
  },
  {
    "pcgw_name": "Engine:LORE",
    "pcgw_url": "//pcgamingwiki.com/wiki/Engine:LORE",
    "wikipedia": null,
    "wikipedia_url": null
  },
  {
    "pcgw_name": "Engine:LS3D",
    "pcgw_url": "//pcgamingwiki.com/wiki/Engine:LS3D",
    "wikipedia": null,
    "wikipedia_url": null
  },
  {
    "pcgw_name": "Engine:LWJGL",
    "pcgw_url": "//pcgamingwiki.com/wiki/Engine:LWJGL",
    "wikipedia": "Lightweight Java Game Library",
    "wikipedia_url": "https://en.wikipedia.org/wiki/Lightweight_Java_Game_Library"
  },
  {
    "pcgw_name": "Engine:Liquid",
    "pcgw_url": "//pcgamingwiki.com/wiki/Engine:Liquid",
    "wikipedia": null,
    "wikipedia_url": null
  },
  {
    "pcgw_name": "Engine:LithTech",
    "pcgw_url": "//pcgamingwiki.com/wiki/Engine:LithTech",
    "wikipedia": "LithTech",
    "wikipedia_url": "https://en.wikipedia.org/wiki/LithTech"
  },
  {
    "pcgw_name": "Engine:Lithtech Jupiter",
    "pcgw_url": "//pcgamingwiki.com/wiki/Engine:Lithtech_Jupiter",
    "wikipedia": "LithTech#LithTech Jupiter",
    "wikipedia_url": "https://en.wikipedia.org/wiki/LithTech#LithTech_Jupiter"
  },
  {
    "pcgw_name": "Engine:Lithtech Jupiter EX",
    "pcgw_url": "//pcgamingwiki.com/wiki/Engine:Lithtech_Jupiter_EX",
    "wikipedia": "LithTech#LithTech Jupiter EX",
    "wikipedia_url": "https://en.wikipedia.org/wiki/LithTech#LithTech_Jupiter_EX"
  },
  {
    "pcgw_name": "Engine:Luminous Studio",
    "pcgw_url": "//pcgamingwiki.com/wiki/Engine:Luminous_Studio",
    "wikipedia": "Luminous Studio",
    "wikipedia_url": "https://en.wikipedia.org/wiki/Luminous_Studio"
  },
  {
    "pcgw_name": "Engine:LyN",
    "pcgw_url": "//pcgamingwiki.com/wiki/Engine:LyN",
    "wikipedia": "LyN (game engine)",
    "wikipedia_url": "https://en.wikipedia.org/wiki/LyN_(game_engine)"
  },
  {
    "pcgw_name": "Engine:Lycium",
    "pcgw_url": "//pcgamingwiki.com/wiki/Engine:Lycium",
    "wikipedia": "BioWare#Technology",
    "wikipedia_url": "https://en.wikipedia.org/wiki/BioWare#Technology"
  },
  {
    "pcgw_name": "Engine:LÖVE",
    "pcgw_url": "//pcgamingwiki.com/wiki/Engine:L%C3%96VE",
    "wikipedia": null,
    "wikipedia_url": null
  },
  {
    "pcgw_name": "Engine:MAX-FX",
    "pcgw_url": "//pcgamingwiki.com/wiki/Engine:MAX-FX",
    "wikipedia": null,
    "wikipedia_url": null
  },
  {
    "pcgw_name": "Engine:MT Framework",
    "pcgw_url": "//pcgamingwiki.com/wiki/Engine:MT_Framework",
    "wikipedia": "MT_Framework",
    "wikipedia_url": "https://en.wikipedia.org/wiki/MT_Framework"
  },
  {
    "pcgw_name": "Engine:Madness Engine",
    "pcgw_url": "//pcgamingwiki.com/wiki/Engine:Madness_Engine",
    "wikipedia": null,
    "wikipedia_url": null
  },
  {
    "pcgw_name": "Engine:Marathon Engine",
    "pcgw_url": "//pcgamingwiki.com/wiki/Engine:Marathon_Engine",
    "wikipedia": null,
    "wikipedia_url": null
  },
  {
    "pcgw_name": "Engine:Marmalade",
    "pcgw_url": "//pcgamingwiki.com/wiki/Engine:Marmalade",
    "wikipedia": "Marmalade (software)",
    "wikipedia_url": "https://en.wikipedia.org/wiki/Marmalade_(software)"
  },
  {
    "pcgw_name": "Engine:MassTech",
    "pcgw_url": "//pcgamingwiki.com/wiki/Engine:MassTech",
    "wikipedia": null,
    "wikipedia_url": null
  },
  {
    "pcgw_name": "Engine:MegaEx",
    "pcgw_url": "//pcgamingwiki.com/wiki/Engine:MegaEx",
    "wikipedia": null,
    "wikipedia_url": null
  },
  {
    "pcgw_name": "Engine:Meng",
    "pcgw_url": "//pcgamingwiki.com/wiki/Engine:Meng",
    "wikipedia": null,
    "wikipedia_url": null
  },
  {
    "pcgw_name": "Engine:Mercury Engine",
    "pcgw_url": "//pcgamingwiki.com/wiki/Engine:Mercury_Engine",
    "wikipedia": null,
    "wikipedia_url": null
  },
  {
    "pcgw_name": "Engine:Merkury Engine",
    "pcgw_url": "//pcgamingwiki.com/wiki/Engine:Merkury_Engine",
    "wikipedia": null,
    "wikipedia_url": null
  },
  {
    "pcgw_name": "Engine:Mkxp",
    "pcgw_url": "//pcgamingwiki.com/wiki/Engine:Mkxp",
    "wikipedia": null,
    "wikipedia_url": null
  },
  {
    "pcgw_name": "Engine:Moai",
    "pcgw_url": "//pcgamingwiki.com/wiki/Engine:Moai",
    "wikipedia": "Moai (software)",
    "wikipedia_url": "https://en.wikipedia.org/wiki/Moai_(software)"
  },
  {
    "pcgw_name": "Engine:Mohawk Engine",
    "pcgw_url": "//pcgamingwiki.com/wiki/Engine:Mohawk_Engine",
    "wikipedia": null,
    "wikipedia_url": null
  },
  {
    "pcgw_name": "Engine:MonoGame",
    "pcgw_url": "//pcgamingwiki.com/wiki/Engine:MonoGame",
    "wikipedia": "MonoGame",
    "wikipedia_url": "https://en.wikipedia.org/wiki/MonoGame"
  },
  {
    "pcgw_name": "Engine:NeoAxis",
    "pcgw_url": "//pcgamingwiki.com/wiki/Engine:NeoAxis",
    "wikipedia": null,
    "wikipedia_url": null
  },
  {
    "pcgw_name": "Engine:Neon",
    "pcgw_url": "//pcgamingwiki.com/wiki/Engine:Neon",
    "wikipedia": "EGO (game engine)",
    "wikipedia_url": "https://en.wikipedia.org/wiki/EGO_(game_engine)"
  },
  {
    "pcgw_name": "Engine:Nitrous",
    "pcgw_url": "//pcgamingwiki.com/wiki/Engine:Nitrous",
    "wikipedia": null,
    "wikipedia_url": null
  },
  {
    "pcgw_name": "Engine:Nocturne",
    "pcgw_url": "//pcgamingwiki.com/wiki/Engine:Nocturne",
    "wikipedia": null,
    "wikipedia_url": null
  },
  {
    "pcgw_name": "Engine:Northlight Engine",
    "pcgw_url": "//pcgamingwiki.com/wiki/Engine:Northlight_Engine",
    "wikipedia": null,
    "wikipedia_url": null
  },
  {
    "pcgw_name": "Engine:OEngine",
    "pcgw_url": "//pcgamingwiki.com/wiki/Engine:OEngine",
    "wikipedia": null,
    "wikipedia_url": null
  },
  {
    "pcgw_name": "Engine:Octane",
    "pcgw_url": "//pcgamingwiki.com/wiki/Engine:Octane",
    "wikipedia": "Firebrand Games#Octane Engine",
    "wikipedia_url": "https://en.wikipedia.org/wiki/Firebrand_Games#Octane_Engine"
  },
  {
    "pcgw_name": "Engine:Odin",
    "pcgw_url": "//pcgamingwiki.com/wiki/Engine:Odin",
    "wikipedia": null,
    "wikipedia_url": null
  },
  {
    "pcgw_name": "Engine:Odyssey",
    "pcgw_url": "//pcgamingwiki.com/wiki/Engine:Odyssey",
    "wikipedia": "BioWare#Technology",
    "wikipedia_url": "https://en.wikipedia.org/wiki/BioWare#Technology"
  },
  {
    "pcgw_name": "Engine:Ogre",
    "pcgw_url": "//pcgamingwiki.com/wiki/Engine:Ogre",
    "wikipedia": "OGRE",
    "wikipedia_url": "https://en.wikipedia.org/wiki/OGRE"
  },
  {
    "pcgw_name": "Engine:Omen Engine",
    "pcgw_url": "//pcgamingwiki.com/wiki/Engine:Omen_Engine",
    "wikipedia": null,
    "wikipedia_url": null
  },
  {
    "pcgw_name": "Engine:Onyx",
    "pcgw_url": "//pcgamingwiki.com/wiki/Engine:Onyx",
    "wikipedia": null,
    "wikipedia_url": null
  },
  {
    "pcgw_name": "Engine:OpenFL",
    "pcgw_url": "//pcgamingwiki.com/wiki/Engine:OpenFL",
    "wikipedia": "OpenFL",
    "wikipedia_url": "https://en.wikipedia.org/wiki/OpenFL"
  },
  {
    "pcgw_name": "Engine:Pain Engine",
    "pcgw_url": "//pcgamingwiki.com/wiki/Engine:Pain_Engine",
    "wikipedia": null,
    "wikipedia_url": null
  },
  {
    "pcgw_name": "Engine:Phoenix",
    "pcgw_url": "//pcgamingwiki.com/wiki/Engine:Phoenix",
    "wikipedia": null,
    "wikipedia_url": null
  },
  {
    "pcgw_name": "Engine:Phoenix3D",
    "pcgw_url": "//pcgamingwiki.com/wiki/Engine:Phoenix3D",
    "wikipedia": null,
    "wikipedia_url": null
  },
  {
    "pcgw_name": "Engine:PhyreEngine",
    "pcgw_url": "//pcgamingwiki.com/wiki/Engine:PhyreEngine",
    "wikipedia": "PhyreEngine",
    "wikipedia_url": "https://en.wikipedia.org/wiki/PhyreEngine"
  },
  {
    "pcgw_name": "Engine:Platinum Engine",
    "pcgw_url": "//pcgamingwiki.com/wiki/Engine:Platinum_Engine",
    "wikipedia": null,
    "wikipedia_url": null
  },
  {
    "pcgw_name": "Engine:PlayGround SDK",
    "pcgw_url": "//pcgamingwiki.com/wiki/Engine:PlayGround_SDK",
    "wikipedia": "PlayFirst#Playground SDK",
    "wikipedia_url": "https://en.wikipedia.org/wiki/PlayFirst#Playground_SDK"
  },
  {
    "pcgw_name": "Engine:PopCap Games Framework",
    "pcgw_url": "//pcgamingwiki.com/wiki/Engine:PopCap_Games_Framework",
    "wikipedia": "PopCap_Games#PopCap_Games_Framework",
    "wikipedia_url": "https://en.wikipedia.org/wiki/PopCap_Games#PopCap_Games_Framework"
  },
  {
    "pcgw_name": "Engine:Prism3D",
    "pcgw_url": "//pcgamingwiki.com/wiki/Engine:Prism3D",
    "wikipedia": null,
    "wikipedia_url": null
  },
  {
    "pcgw_name": "Engine:Ptero Engine",
    "pcgw_url": "//pcgamingwiki.com/wiki/Engine:Ptero_Engine",
    "wikipedia": null,
    "wikipedia_url": null
  },
  {
    "pcgw_name": "Engine:Ptero Engine II",
    "pcgw_url": "//pcgamingwiki.com/wiki/Engine:Ptero_Engine_II",
    "wikipedia": null,
    "wikipedia_url": null
  },
  {
    "pcgw_name": "Engine:Ptero Engine III",
    "pcgw_url": "//pcgamingwiki.com/wiki/Engine:Ptero_Engine_III",
    "wikipedia": null,
    "wikipedia_url": null
  },
  {
    "pcgw_name": "Engine:Pure3D",
    "pcgw_url": "//pcgamingwiki.com/wiki/Engine:Pure3D",
    "wikipedia": null,
    "wikipedia_url": null
  },
  {
    "pcgw_name": "Engine:Pyrogenesis",
    "pcgw_url": "//pcgamingwiki.com/wiki/Engine:Pyrogenesis",
    "wikipedia": null,
    "wikipedia_url": null
  },
  {
    "pcgw_name": "Engine:Quake engine",
    "pcgw_url": "//pcgamingwiki.com/wiki/Engine:Quake_engine",
    "wikipedia": "Quake engine",
    "wikipedia_url": "https://en.wikipedia.org/wiki/Quake_engine"
  },
  {
    "pcgw_name": "Engine:QuakeWorld",
    "pcgw_url": "//pcgamingwiki.com/wiki/Engine:QuakeWorld",
    "wikipedia": "QuakeWorld",
    "wikipedia_url": "https://en.wikipedia.org/wiki/QuakeWorld"
  },
  {
    "pcgw_name": "Engine:Quest3D",
    "pcgw_url": "//pcgamingwiki.com/wiki/Engine:Quest3D",
    "wikipedia": null,
    "wikipedia_url": null
  },
  {
    "pcgw_name": "Engine:RAGE",
    "pcgw_url": "//pcgamingwiki.com/wiki/Engine:RAGE",
    "wikipedia": "Rockstar Advanced Game Engine",
    "wikipedia_url": "https://en.wikipedia.org/wiki/Rockstar_Advanced_Game_Engine"
  },
  {
    "pcgw_name": "Engine:RE Engine",
    "pcgw_url": "//pcgamingwiki.com/wiki/Engine:RE_Engine",
    "wikipedia": null,
    "wikipedia_url": null
  },
  {
    "pcgw_name": "Engine:REDengine",
    "pcgw_url": "//pcgamingwiki.com/wiki/Engine:REDengine",
    "wikipedia": "REDengine",
    "wikipedia_url": "https://en.wikipedia.org/wiki/REDengine"
  },
  {
    "pcgw_name": "Engine:ROMU Engine",
    "pcgw_url": "//pcgamingwiki.com/wiki/Engine:ROMU_Engine",
    "wikipedia": null,
    "wikipedia_url": null
  },
  {
    "pcgw_name": "Engine:RPG Maker",
    "pcgw_url": "//pcgamingwiki.com/wiki/Engine:RPG_Maker",
    "wikipedia": "RPG Maker",
    "wikipedia_url": "https://en.wikipedia.org/wiki/RPG_Maker"
  },
  {
    "pcgw_name": "Engine:Raven engine",
    "pcgw_url": "//pcgamingwiki.com/wiki/Engine:Raven_engine",
    "wikipedia": null,
    "wikipedia_url": null
  },
  {
    "pcgw_name": "Engine:Real Virtuality",
    "pcgw_url": "//pcgamingwiki.com/wiki/Engine:Real_Virtuality",
    "wikipedia": "Real Virtuality (game engine)",
    "wikipedia_url": "https://en.wikipedia.org/wiki/Real_Virtuality_(game_engine)"
  },
  {
    "pcgw_name": "Engine:RealLive",
    "pcgw_url": "//pcgamingwiki.com/wiki/Engine:RealLive",
    "wikipedia": null,
    "wikipedia_url": null
  },
  {
    "pcgw_name": "Engine:Refractor",
    "pcgw_url": "//pcgamingwiki.com/wiki/Engine:Refractor",
    "wikipedia": "Refractor Engine",
    "wikipedia_url": "https://en.wikipedia.org/wiki/Refractor_Engine"
  },
  {
    "pcgw_name": "Engine:Refractor 2",
    "pcgw_url": "//pcgamingwiki.com/wiki/Engine:Refractor_2",
    "wikipedia": "Refractor Engine",
    "wikipedia_url": "https://en.wikipedia.org/wiki/Refractor_Engine"
  },
  {
    "pcgw_name": "Engine:Ren'Py",
    "pcgw_url": "//pcgamingwiki.com/wiki/Engine:Ren%27Py",
    "wikipedia": "Ren'Py",
    "wikipedia_url": "https://en.wikipedia.org/wiki/Ren'Py"
  },
  {
    "pcgw_name": "Engine:RenderWare",
    "pcgw_url": "//pcgamingwiki.com/wiki/Engine:RenderWare",
    "wikipedia": "RenderWare",
    "wikipedia_url": "https://en.wikipedia.org/wiki/RenderWare"
  },
  {
    "pcgw_name": "Engine:Replay Engine",
    "pcgw_url": "//pcgamingwiki.com/wiki/Engine:Replay_Engine",
    "wikipedia": null,
    "wikipedia_url": null
  },
  {
    "pcgw_name": "Engine:Retaliator",
    "pcgw_url": "//pcgamingwiki.com/wiki/Engine:Retaliator",
    "wikipedia": null,
    "wikipedia_url": null
  },
  {
    "pcgw_name": "Engine:Retro Engine",
    "pcgw_url": "//pcgamingwiki.com/wiki/Engine:Retro_Engine",
    "wikipedia": "Retro Engine",
    "wikipedia_url": "https://en.wikipedia.org/wiki/Retro_Engine"
  },
  {
    "pcgw_name": "Engine:Riot Engine",
    "pcgw_url": "//pcgamingwiki.com/wiki/Engine:Riot_Engine",
    "wikipedia": "Riot Engine",
    "wikipedia_url": "https://en.wikipedia.org/wiki/Riot_Engine"
  },
  {
    "pcgw_name": "Engine:Road Hog Engine",
    "pcgw_url": "//pcgamingwiki.com/wiki/Engine:Road_Hog_Engine",
    "wikipedia": "Flying Wild Hog#Road Hog Engine",
    "wikipedia_url": "https://en.wikipedia.org/wiki/Flying_Wild_Hog#Road_Hog_Engine"
  },
  {
    "pcgw_name": "Engine:Rockstar Leeds 3D Engine",
    "pcgw_url": "//pcgamingwiki.com/wiki/Engine:Rockstar_Leeds_3D_Engine",
    "wikipedia": null,
    "wikipedia_url": null
  },
  {
    "pcgw_name": "Engine:SAGE",
    "pcgw_url": "//pcgamingwiki.com/wiki/Engine:SAGE",
    "wikipedia": "SAGE (game engine)",
    "wikipedia_url": "https://en.wikipedia.org/wiki/SAGE_(game_engine)"
  },
  {
    "pcgw_name": "Engine:SAGE 2.0",
    "pcgw_url": "//pcgamingwiki.com/wiki/Engine:SAGE_2.0",
    "wikipedia": "SAGE (game engine)",
    "wikipedia_url": "https://en.wikipedia.org/wiki/SAGE_(game_engine)"
  },
  {
    "pcgw_name": "Engine:SCI",
    "pcgw_url": "//pcgamingwiki.com/wiki/Engine:SCI",
    "wikipedia": "Sierra%27s_Creative_Interpreter",
    "wikipedia_url": "https://en.wikipedia.org/wiki/Sierra%27s_Creative_Interpreter"
  },
  {
    "pcgw_name": "Engine:SCUMM",
    "pcgw_url": "//pcgamingwiki.com/wiki/Engine:SCUMM",
    "wikipedia": "SCUMM",
    "wikipedia_url": "https://en.wikipedia.org/wiki/SCUMM"
  },
  {
    "pcgw_name": "Engine:SFML",
    "pcgw_url": "//pcgamingwiki.com/wiki/Engine:SFML",
    "wikipedia": "Simple and Fast Multimedia Library",
    "wikipedia_url": "https://en.wikipedia.org/wiki/Simple_and_Fast_Multimedia_Library"
  },
  {
    "pcgw_name": "Engine:STEM Engine",
    "pcgw_url": "//pcgamingwiki.com/wiki/Engine:STEM_Engine",
    "wikipedia": null,
    "wikipedia_url": null
  },
  {
    "pcgw_name": "Engine:Saber3D Engine",
    "pcgw_url": "//pcgamingwiki.com/wiki/Engine:Saber3D_Engine",
    "wikipedia": "Saber Interactive#Saber3D Engine",
    "wikipedia_url": "https://en.wikipedia.org/wiki/Saber_Interactive#Saber3D_Engine"
  },
  {
    "pcgw_name": "Engine:Sauerbraten",
    "pcgw_url": "//pcgamingwiki.com/wiki/Engine:Sauerbraten",
    "wikipedia": null,
    "wikipedia_url": null
  },
  {
    "pcgw_name": "Engine:Scimitar",
    "pcgw_url": "//pcgamingwiki.com/wiki/Engine:Scimitar",
    "wikipedia": "Anvil (game engine)",
    "wikipedia_url": "https://en.wikipedia.org/wiki/Anvil_(game_engine)"
  },
  {
    "pcgw_name": "Engine:ScummVM",
    "pcgw_url": "//pcgamingwiki.com/wiki/Engine:ScummVM",
    "wikipedia": "ScummVM",
    "wikipedia_url": "https://en.wikipedia.org/wiki/ScummVM"
  },
  {
    "pcgw_name": "Engine:Serious Engine",
    "pcgw_url": "//pcgamingwiki.com/wiki/Engine:Serious_Engine",
    "wikipedia": "Croteam#Serious Engine",
    "wikipedia_url": "https://en.wikipedia.org/wiki/Croteam#Serious_Engine"
  },
  {
    "pcgw_name": "Engine:Shark 3D",
    "pcgw_url": "//pcgamingwiki.com/wiki/Engine:Shark_3D",
    "wikipedia": "Shark_3D",
    "wikipedia_url": "https://en.wikipedia.org/wiki/Shark_3D"
  },
  {
    "pcgw_name": "Engine:ShiVa Engine",
    "pcgw_url": "//pcgamingwiki.com/wiki/Engine:ShiVa_Engine",
    "wikipedia": "ShiVa",
    "wikipedia_url": "https://en.wikipedia.org/wiki/ShiVa"
  },
  {
    "pcgw_name": "Engine:SiglusEngine",
    "pcgw_url": "//pcgamingwiki.com/wiki/Engine:SiglusEngine",
    "wikipedia": null,
    "wikipedia_url": null
  },
  {
    "pcgw_name": "Engine:Silent Storm Engine",
    "pcgw_url": "//pcgamingwiki.com/wiki/Engine:Silent_Storm_Engine",
    "wikipedia": "Silent Storm engine",
    "wikipedia_url": "https://en.wikipedia.org/wiki/Silent_Storm_engine"
  },
  {
    "pcgw_name": "Engine:Silk",
    "pcgw_url": "//pcgamingwiki.com/wiki/Engine:Silk",
    "wikipedia": null,
    "wikipedia_url": null
  },
  {
    "pcgw_name": "Engine:SilverWare",
    "pcgw_url": "//pcgamingwiki.com/wiki/Engine:SilverWare",
    "wikipedia": null,
    "wikipedia_url": null
  },
  {
    "pcgw_name": "Engine:Sith",
    "pcgw_url": "//pcgamingwiki.com/wiki/Engine:Sith",
    "wikipedia": "Sith (game engine)",
    "wikipedia_url": "https://en.wikipedia.org/wiki/Sith_(game_engine)"
  },
  {
    "pcgw_name": "Engine:Slayer",
    "pcgw_url": "//pcgamingwiki.com/wiki/Engine:Slayer",
    "wikipedia": null,
    "wikipedia_url": null
  },
  {
    "pcgw_name": "Engine:SmartSim",
    "pcgw_url": "//pcgamingwiki.com/wiki/Engine:SmartSim",
    "wikipedia": null,
    "wikipedia_url": null
  },
  {
    "pcgw_name": "Engine:Snowdrop Engine",
    "pcgw_url": "//pcgamingwiki.com/wiki/Engine:Snowdrop_Engine",
    "wikipedia": "Snowdrop (game engine)",
    "wikipedia_url": "https://en.wikipedia.org/wiki/Snowdrop_(game_engine)"
  },
  {
    "pcgw_name": "Engine:Source",
    "pcgw_url": "//pcgamingwiki.com/wiki/Engine:Source",
    "wikipedia": "Source (game engine)",
    "wikipedia_url": "https://en.wikipedia.org/wiki/Source_(game_engine)"
  },
  {
    "pcgw_name": "Engine:Source 2",
    "pcgw_url": "//pcgamingwiki.com/wiki/Engine:Source_2",
    "wikipedia": "Source 2",
    "wikipedia_url": "https://en.wikipedia.org/wiki/Source_2"
  },
  {
    "pcgw_name": "Engine:Stencyl",
    "pcgw_url": "//pcgamingwiki.com/wiki/Engine:Stencyl",
    "wikipedia": "Stencyl",
    "wikipedia_url": "https://en.wikipedia.org/wiki/Stencyl"
  },
  {
    "pcgw_name": "Engine:Sumo Engine",
    "pcgw_url": "//pcgamingwiki.com/wiki/Engine:Sumo_Engine",
    "wikipedia": null,
    "wikipedia_url": null
  },
  {
    "pcgw_name": "Engine:System4",
    "pcgw_url": "//pcgamingwiki.com/wiki/Engine:System4",
    "wikipedia": null,
    "wikipedia_url": null
  },
  {
    "pcgw_name": "Engine:TED engine",
    "pcgw_url": "//pcgamingwiki.com/wiki/Engine:TED_engine",
    "wikipedia": null,
    "wikipedia_url": null
  },
  {
    "pcgw_name": "Engine:Telltale Tool",
    "pcgw_url": "//pcgamingwiki.com/wiki/Engine:Telltale_Tool",
    "wikipedia": "Telltale Games#Telltale Tool",
    "wikipedia_url": "https://en.wikipedia.org/wiki/Telltale_Games#Telltale_Tool"
  },
  {
    "pcgw_name": "Engine:The Sims 2 Engine",
    "pcgw_url": "//pcgamingwiki.com/wiki/Engine:The_Sims_2_Engine",
    "wikipedia": null,
    "wikipedia_url": null
  },
  {
    "pcgw_name": "Engine:The Sims 3 Engine",
    "pcgw_url": "//pcgamingwiki.com/wiki/Engine:The_Sims_3_Engine",
    "wikipedia": null,
    "wikipedia_url": null
  },
  {
    "pcgw_name": "Engine:The Sims Engine",
    "pcgw_url": "//pcgamingwiki.com/wiki/Engine:The_Sims_Engine",
    "wikipedia": null,
    "wikipedia_url": null
  },
  {
    "pcgw_name": "Engine:TheEngine",
    "pcgw_url": "//pcgamingwiki.com/wiki/Engine:TheEngine",
    "wikipedia": "TheEngine",
    "wikipedia_url": "https://en.wikipedia.org/wiki/TheEngine"
  },
  {
    "pcgw_name": "Engine:Titan",
    "pcgw_url": "//pcgamingwiki.com/wiki/Engine:Titan",
    "wikipedia": "Titan (game engine)",
    "wikipedia_url": "https://en.wikipedia.org/wiki/Titan_(game_engine)"
  },
  {
    "pcgw_name": "Engine:Titanium",
    "pcgw_url": "//pcgamingwiki.com/wiki/Engine:Titanium",
    "wikipedia": "Radical Entertainment#Titanium Engine",
    "wikipedia_url": "https://en.wikipedia.org/wiki/Radical_Entertainment#Titanium_Engine"
  },
  {
    "pcgw_name": "Engine:Torque",
    "pcgw_url": "//pcgamingwiki.com/wiki/Engine:Torque",
    "wikipedia": "Torque_(game_engine)",
    "wikipedia_url": "https://en.wikipedia.org/wiki/Torque_(game_engine)"
  },
  {
    "pcgw_name": "Engine:Traktor",
    "pcgw_url": "//pcgamingwiki.com/wiki/Engine:Traktor",
    "wikipedia": null,
    "wikipedia_url": null
  },
  {
    "pcgw_name": "Engine:True 3D",
    "pcgw_url": "//pcgamingwiki.com/wiki/Engine:True_3D",
    "wikipedia": null,
    "wikipedia_url": null
  },
  {
    "pcgw_name": "Engine:Twilight 2",
    "pcgw_url": "//pcgamingwiki.com/wiki/Engine:Twilight_2",
    "wikipedia": "Twilight 2",
    "wikipedia_url": "https://en.wikipedia.org/wiki/Twilight_2"
  },
  {
    "pcgw_name": "Engine:Twine",
    "pcgw_url": "//pcgamingwiki.com/wiki/Engine:Twine",
    "wikipedia": "Twine_(software)",
    "wikipedia_url": "https://en.wikipedia.org/wiki/Twine_(software)"
  },
  {
    "pcgw_name": "Engine:TyranoBuilder",
    "pcgw_url": "//pcgamingwiki.com/wiki/Engine:TyranoBuilder",
    "wikipedia": null,
    "wikipedia_url": null
  },
  {
    "pcgw_name": "Engine:UbiArt Framework",
    "pcgw_url": "//pcgamingwiki.com/wiki/Engine:UbiArt_Framework",
    "wikipedia": "UbiArt Framework",
    "wikipedia_url": "https://en.wikipedia.org/wiki/UbiArt_Framework"
  },
  {
    "pcgw_name": "Engine:Ubisoft OpenSpace",
    "pcgw_url": "//pcgamingwiki.com/wiki/Engine:Ubisoft_OpenSpace",
    "wikipedia": null,
    "wikipedia_url": null
  },
  {
    "pcgw_name": "Engine:Underworld engine",
    "pcgw_url": "//pcgamingwiki.com/wiki/Engine:Underworld_engine",
    "wikipedia": null,
    "wikipedia_url": null
  },
  {
    "pcgw_name": "Engine:Unigine",
    "pcgw_url": "//pcgamingwiki.com/wiki/Engine:Unigine",
    "wikipedia": "Unigine",
    "wikipedia_url": "https://en.wikipedia.org/wiki/Unigine"
  },
  {
    "pcgw_name": "Engine:Unity",
    "pcgw_url": "//pcgamingwiki.com/wiki/Engine:Unity",
    "wikipedia": "Unity (game engine)",
    "wikipedia_url": "https://en.wikipedia.org/wiki/Unity_(game_engine)"
  },
  {
    "pcgw_name": "Engine:Unreal Engine 1",
    "pcgw_url": "//pcgamingwiki.com/wiki/Engine:Unreal_Engine_1",
    "wikipedia": "Unreal engine#Unreal Engine 1",
    "wikipedia_url": "https://en.wikipedia.org/wiki/Unreal_engine#Unreal_Engine_1"
  },
  {
    "pcgw_name": "Engine:Unreal Engine 2",
    "pcgw_url": "//pcgamingwiki.com/wiki/Engine:Unreal_Engine_2",
    "wikipedia": "Unreal engine#Unreal Engine 2",
    "wikipedia_url": "https://en.wikipedia.org/wiki/Unreal_engine#Unreal_Engine_2"
  },
  {
    "pcgw_name": "Engine:Unreal Engine 2.5",
    "pcgw_url": "//pcgamingwiki.com/wiki/Engine:Unreal_Engine_2.5",
    "wikipedia": "Unreal engine#Unreal Engine 2",
    "wikipedia_url": "https://en.wikipedia.org/wiki/Unreal_engine#Unreal_Engine_2"
  },
  {
    "pcgw_name": "Engine:Unreal Engine 3",
    "pcgw_url": "//pcgamingwiki.com/wiki/Engine:Unreal_Engine_3",
    "wikipedia": "Unreal engine#Unreal Engine 3",
    "wikipedia_url": "https://en.wikipedia.org/wiki/Unreal_engine#Unreal_Engine_3"
  },
  {
    "pcgw_name": "Engine:Unreal Engine 4",
    "pcgw_url": "//pcgamingwiki.com/wiki/Engine:Unreal_Engine_4",
    "wikipedia": "Unreal Engine#Unreal Engine 4",
    "wikipedia_url": "https://en.wikipedia.org/wiki/Unreal_Engine#Unreal_Engine_4"
  },
  {
    "pcgw_name": "Engine:V-Cruise",
    "pcgw_url": "//pcgamingwiki.com/wiki/Engine:V-Cruise",
    "wikipedia": "Detalion#V-Cruise engine",
    "wikipedia_url": "https://en.wikipedia.org/wiki/Detalion#V-Cruise_engine"
  },
  {
    "pcgw_name": "Engine:VRAGE",
    "pcgw_url": "//pcgamingwiki.com/wiki/Engine:VRAGE",
    "wikipedia": "Keen Software House#VRAGE",
    "wikipedia_url": "https://en.wikipedia.org/wiki/Keen_Software_House#VRAGE"
  },
  {
    "pcgw_name": "Engine:Vicarious Visions Alchemy",
    "pcgw_url": "//pcgamingwiki.com/wiki/Engine:Vicarious_Visions_Alchemy",
    "wikipedia": null,
    "wikipedia_url": null
  },
  {
    "pcgw_name": "Engine:Vicious Engine",
    "pcgw_url": "//pcgamingwiki.com/wiki/Engine:Vicious_Engine",
    "wikipedia": "Vicious Engine",
    "wikipedia_url": "https://en.wikipedia.org/wiki/Vicious_Engine"
  },
  {
    "pcgw_name": "Engine:Virtools",
    "pcgw_url": "//pcgamingwiki.com/wiki/Engine:Virtools",
    "wikipedia": "Virtools",
    "wikipedia_url": "https://en.wikipedia.org/wiki/Virtools"
  },
  {
    "pcgw_name": "Engine:Virtual Theatre",
    "pcgw_url": "//pcgamingwiki.com/wiki/Engine:Virtual_Theatre",
    "wikipedia": "Virtual_Theatre",
    "wikipedia_url": "https://en.wikipedia.org/wiki/Virtual_Theatre"
  },
  {
    "pcgw_name": "Engine:Vision",
    "pcgw_url": "//pcgamingwiki.com/wiki/Engine:Vision",
    "wikipedia": "Vision_(game_engine)",
    "wikipedia_url": "https://en.wikipedia.org/wiki/Vision_(game_engine)"
  },
  {
    "pcgw_name": "Engine:Visionaire",
    "pcgw_url": "//pcgamingwiki.com/wiki/Engine:Visionaire",
    "wikipedia": null,
    "wikipedia_url": null
  },
  {
    "pcgw_name": "Engine:Void Engine",
    "pcgw_url": "//pcgamingwiki.com/wiki/Engine:Void_Engine",
    "wikipedia": null,
    "wikipedia_url": null
  },
  {
    "pcgw_name": "Engine:Vostok Engine",
    "pcgw_url": "//pcgamingwiki.com/wiki/Engine:Vostok_Engine",
    "wikipedia": null,
    "wikipedia_url": null
  },
  {
    "pcgw_name": "Engine:Voxlap",
    "pcgw_url": "//pcgamingwiki.com/wiki/Engine:Voxlap",
    "wikipedia": null,
    "wikipedia_url": null
  },
  {
    "pcgw_name": "Engine:WF Engine",
    "pcgw_url": "//pcgamingwiki.com/wiki/Engine:WF_Engine",
    "wikipedia": null,
    "wikipedia_url": null
  },
  {
    "pcgw_name": "Engine:WOLF RPG Editor",
    "pcgw_url": "//pcgamingwiki.com/wiki/Engine:WOLF_RPG_Editor",
    "wikipedia": null,
    "wikipedia_url": null
  },
  {
    "pcgw_name": "Engine:Warscape",
    "pcgw_url": "//pcgamingwiki.com/wiki/Engine:Warscape",
    "wikipedia": null,
    "wikipedia_url": null
  },
  {
    "pcgw_name": "Engine:Westwood 3D",
    "pcgw_url": "//pcgamingwiki.com/wiki/Engine:Westwood_3D",
    "wikipedia": "SAGE_(game_engine)",
    "wikipedia_url": "https://en.wikipedia.org/wiki/SAGE_(game_engine)"
  },
  {
    "pcgw_name": "Engine:Wintermute",
    "pcgw_url": "//pcgamingwiki.com/wiki/Engine:Wintermute",
    "wikipedia": "Wintermute Engine",
    "wikipedia_url": "https://en.wikipedia.org/wiki/Wintermute_Engine"
  },
  {
    "pcgw_name": "Engine:With the Love Engine",
    "pcgw_url": "//pcgamingwiki.com/wiki/Engine:With_the_Love_Engine",
    "wikipedia": null,
    "wikipedia_url": null
  },
  {
    "pcgw_name": "Engine:Wolfenstein 3D engine",
    "pcgw_url": "//pcgamingwiki.com/wiki/Engine:Wolfenstein_3D_engine",
    "wikipedia": "Wolfenstein 3D engine",
    "wikipedia_url": "https://en.wikipedia.org/wiki/Wolfenstein_3D_engine"
  },
  {
    "pcgw_name": "Engine:World Builder",
    "pcgw_url": "//pcgamingwiki.com/wiki/Engine:World_Builder",
    "wikipedia": null,
    "wikipedia_url": null
  },
  {
    "pcgw_name": "Engine:X-Ray Engine",
    "pcgw_url": "//pcgamingwiki.com/wiki/Engine:X-Ray_Engine",
    "wikipedia": "X-Ray Engine",
    "wikipedia_url": "https://en.wikipedia.org/wiki/X-Ray_Engine"
  },
  {
    "pcgw_name": "Engine:XNA",
    "pcgw_url": "//pcgamingwiki.com/wiki/Engine:XNA",
    "wikipedia": "Microsoft XNA",
    "wikipedia_url": "https://en.wikipedia.org/wiki/Microsoft_XNA"
  },
  {
    "pcgw_name": "Engine:XnGine",
    "pcgw_url": "//pcgamingwiki.com/wiki/Engine:XnGine",
    "wikipedia": "XnGine",
    "wikipedia_url": "https://en.wikipedia.org/wiki/XnGine"
  },
  {
    "pcgw_name": "Engine:YETI",
    "pcgw_url": "//pcgamingwiki.com/wiki/Engine:YETI",
    "wikipedia": null,
    "wikipedia_url": null
  },
  {
    "pcgw_name": "Engine:Z-Engine",
    "pcgw_url": "//pcgamingwiki.com/wiki/Engine:Z-Engine",
    "wikipedia": null,
    "wikipedia_url": null
  },
  {
    "pcgw_name": "Engine:ZIL",
    "pcgw_url": "//pcgamingwiki.com/wiki/Engine:ZIL",
    "wikipedia": "Z-machine",
    "wikipedia_url": "https://en.wikipedia.org/wiki/Z-machine"
  },
  {
    "pcgw_name": "Engine:ZenGin",
    "pcgw_url": "//pcgamingwiki.com/wiki/Engine:ZenGin",
    "wikipedia": null,
    "wikipedia_url": null
  },
  {
    "pcgw_name": "Engine:Zero",
    "pcgw_url": "//pcgamingwiki.com/wiki/Engine:Zero",
    "wikipedia": "Zero_(game_engine)",
    "wikipedia_url": "https://en.wikipedia.org/wiki/Zero_(game_engine)"
  }
]